debug/__init__.py
debug/accuracy_tools/CMakeLists.txt
debug/accuracy_tools/__init__.py
debug/accuracy_tools/setup.py
debug/accuracy_tools/msprobe/CMakeLists.txt
debug/accuracy_tools/msprobe/__init__.py
debug/accuracy_tools/msprobe/config.json
debug/accuracy_tools/msprobe/msprobe.py
debug/accuracy_tools/msprobe/core/__init__.py
debug/accuracy_tools/msprobe/core/common_config.py
debug/accuracy_tools/msprobe/core/hook_manager.py
debug/accuracy_tools/msprobe/core/service.py
debug/accuracy_tools/msprobe/core/config_check/__init__.py
debug/accuracy_tools/msprobe/core/config_check/config_check_cli.py
debug/accuracy_tools/msprobe/core/config_check/config_checker.py
debug/accuracy_tools/msprobe/core/config_check/checkers/__init__.py
debug/accuracy_tools/msprobe/core/config_check/checkers/base_checker.py
debug/accuracy_tools/msprobe/core/config_check/checkers/dataset_checker.py
debug/accuracy_tools/msprobe/core/config_check/checkers/env_args_checker.py
debug/accuracy_tools/msprobe/core/config_check/checkers/hyperparameter_checker.py
debug/accuracy_tools/msprobe/core/config_check/checkers/pip_checker.py
debug/accuracy_tools/msprobe/core/config_check/checkers/random_checker.py
debug/accuracy_tools/msprobe/core/config_check/checkers/weights_checker.py
debug/accuracy_tools/msprobe/core/grad_probe/__init__.py
debug/accuracy_tools/msprobe/core/grad_probe/constant.py
debug/accuracy_tools/msprobe/core/grad_probe/grad_compare.py
debug/accuracy_tools/msprobe/core/grad_probe/utils.py
debug/accuracy_tools/msprobe/core/monitor/__init__.py
debug/accuracy_tools/msprobe/core/monitor/anomaly_processor.py
debug/accuracy_tools/msprobe/core/monitor/utils.py
debug/accuracy_tools/msprobe/core/single_save/__init__.py
debug/accuracy_tools/msprobe/core/single_save/single_comparator.py
debug/accuracy_tools/msprobe/core/single_save/single_saver.py
debug/accuracy_tools/msprobe/mindspore/__init__.py
debug/accuracy_tools/msprobe/mindspore/cell_processor.py
msprof_analyze-8.1.0.dist-info/LICENSE
msprof_analyze-8.1.0.dist-info/METADATA
msprof_analyze-8.1.0.dist-info/WHEEL
msprof_analyze-8.1.0.dist-info/entry_points.txt
msprof_analyze-8.1.0.dist-info/top_level.txt
msprof_analyze-8.1.0.dist-info/RECORD
